tand/__init__.py
tand/create_project.py
tand/deployment/__init__.py
tand/deployment/aws_elastic_beanstalk.py
tand/structured_data/__init__.py
tand/structured_data/classification/__init__.py
tand/structured_data/classification/pytorch/__init__.py
tand/structured_data/classification/pytorch/create_project.py
tand/structured_data/classification/pytorch/project_template/Dockerfile
tand/structured_data/classification/pytorch/project_template/README.md
tand/structured_data/classification/pytorch/project_template/app.py
tand/structured_data/classification/pytorch/project_template/config.json
tand/structured_data/classification/pytorch/project_template/mlflow-server.sh
tand/structured_data/classification/pytorch/project_template/request_model.json
tand/structured_data/classification/pytorch/project_template/requirements.txt
tand/structured_data/classification/pytorch/project_template/test_app.py
tand/structured_data/classification/pytorch/project_template/train.py
tand/structured_data/classification/pytorch/project_template/data/data.csv
tand/structured_data/classification/pytorch/project_template/env_files/app.env
tand/structured_data/classification/pytorch/project_template/env_files/docker_app.env
tand/structured_data/classification/pytorch/project_template/env_files/train.env
tand/structured_data/classification/pytorch/project_template/lib/__init__.py
tand/structured_data/classification/pytorch/project_template/lib/model.py
tand/structured_data/classification/pytorch/project_template/lib/preprocess.py
tand/structured_data/classification/sklearn/__init__.py
tand/structured_data/classification/sklearn/create_project.py
tand/structured_data/classification/sklearn/project_template/Dockerfile
tand/structured_data/classification/sklearn/project_template/README.md
tand/structured_data/classification/sklearn/project_template/app.py
tand/structured_data/classification/sklearn/project_template/config.json
train_and_deploy-0.1.4.dist-info/METADATA
train_and_deploy-0.1.4.dist-info/WHEEL
train_and_deploy-0.1.4.dist-info/entry_points.txt
train_and_deploy-0.1.4.dist-info/top_level.txt
train_and_deploy-0.1.4.dist-info/RECORD
