Metadata-Version: 2.1
Name: train-and-deploy
Version: 0.1.4
Summary: Train and Deploy is a framework to automatize the Machine Learning workflow.
Home-page: https://github.com/piEsposito/tand
Author: Pi Esposito
License: UNKNOWN
Platform: UNKNOWN
Classifier: Development Status :: 3 - Alpha
Classifier: Intended Audience :: Developers
Classifier: Programming Language :: Python :: 3.8
Requires-Dist: torch (==1.6.0)
Requires-Dist: scikit-learn (==0.22.2)
Requires-Dist: mlflow (==1.10.0)
Requires-Dist: pandas (==1.0.4)
Requires-Dist: numpy (==1.19.1)
Requires-Dist: seaborn (==0.10.1)
Requires-Dist: matplotlib (==3.2.1)
Requires-Dist: unidecode (==1.1.1)
Requires-Dist: fastapi (==0.60.1)
